sonecules/__init__.py
sonecules/base.py
sonecules/bufferson.py
sonecules/scoreson.py
sonecules/triggerson.py
sonecules-0.1.0.dist-info/LICENSE.txt
sonecules-0.1.0.dist-info/METADATA
sonecules-0.1.0.dist-info/WHEEL
sonecules-0.1.0.dist-info/top_level.txt
sonecules-0.1.0.dist-info/RECORD
