Metadata-Version: 2.1
Name: sonecules
Version: 0.1.0
Summary: a Python Sonification Architecture
Home-page: https://github.com/interactive-sonification/sonecules/
Author: Dennis Reinsch, Thomas Hermann
Author-email: dreinsch@techfak.uni-bielefeld.de, thermann@techfak.uni-bielefeld.de
License: MIT
Project-URL: Source, https://github.com/interactive-sonification/sonecules/
Project-URL: Tracker, https://github.com/interactive-sonification/sonecules/issues
Platform: any
Classifier: Development Status :: 4 - Beta
Classifier: Programming Language :: Python
License-File: LICENSE.txt
Requires-Dist: mesonic
Requires-Dist: numpy
Requires-Dist: pandas
Requires-Dist: pya
Requires-Dist: pytsmod
Requires-Dist: importlib-metadata ; python_version < "3.8"
Provides-Extra: all
Requires-Dist: mesonic[sc3nb] ; extra == 'all'
Requires-Dist: setuptools ; extra == 'all'
Requires-Dist: pytest ; extra == 'all'
Requires-Dist: pytest-cov ; extra == 'all'
Provides-Extra: examples
Requires-Dist: ipympl ; extra == 'examples'
Provides-Extra: testing
Requires-Dist: mesonic[sc3nb] ; extra == 'testing'
Requires-Dist: setuptools ; extra == 'testing'
Requires-Dist: pytest ; extra == 'testing'
Requires-Dist: pytest-cov ; extra == 'testing'
